odoo/addons/account_invoice_supplier_self_invoice_tax_note/README.rst
odoo/addons/account_invoice_supplier_self_invoice_tax_note/__init__.py
odoo/addons/account_invoice_supplier_self_invoice_tax_note/__manifest__.py
odoo/addons/account_invoice_supplier_self_invoice_tax_note/i18n/account_invoice_supplier_self_invoice_tax_note.pot
odoo/addons/account_invoice_supplier_self_invoice_tax_note/readme/CONTRIBUTORS.rst
odoo/addons/account_invoice_supplier_self_invoice_tax_note/readme/DESCRIPTION.rst
odoo/addons/account_invoice_supplier_self_invoice_tax_note/readme/INSTALL.rst
odoo/addons/account_invoice_supplier_self_invoice_tax_note/static/description/icon.png
odoo/addons/account_invoice_supplier_self_invoice_tax_note/static/description/index.html
odoo/addons/account_invoice_supplier_self_invoice_tax_note/views/report_self_invoice.xml
odoo11_addon_account_invoice_supplier_self_invoice_tax_note-11.0.1.0.0.99.dev3.dist-info/METADATA
odoo11_addon_account_invoice_supplier_self_invoice_tax_note-11.0.1.0.0.99.dev3.dist-info/WHEEL
odoo11_addon_account_invoice_supplier_self_invoice_tax_note-11.0.1.0.0.99.dev3.dist-info/top_level.txt
odoo11_addon_account_invoice_supplier_self_invoice_tax_note-11.0.1.0.0.99.dev3.dist-info/RECORD
